manim_notebook/__init__.py
manim_notebook/es.py
manim_notebook/fetch_output.py
manim_notebook/mango.py
manim_notebook/manim_cell.py
manim_notebook/parse_args.py
manim_notebook/split.py
manim_notebook-1.0.1.dist-info/LICENSE
manim_notebook-1.0.1.dist-info/METADATA
manim_notebook-1.0.1.dist-info/WHEEL
manim_notebook-1.0.1.dist-info/top_level.txt
manim_notebook-1.0.1.dist-info/RECORD
