Metadata-Version: 2.1
Name: manim-notebook
Version: 1.0.1
Summary: Integrates manim with jupyter notebook
Home-page: https://github.com/AkashKarnatak/manim_notebook
Author: Akash Karnatak
Author-email: akashkarnatak.ak47@gmail.com
License: MIT
Keywords: manim,jupyter,notebook,jupyter notebook,IPython
Platform: UNKNOWN
Classifier: Development Status :: 5 - Production/Stable
Classifier: License :: OSI Approved :: MIT License
Classifier: Programming Language :: Python :: 3.6
Classifier: Programming Language :: Python :: 3.7
Classifier: Programming Language :: Python :: 3.8
Requires-Python: >=3.6
Requires-Dist: IPython
Requires-Dist: manimlib
Requires-Dist: notebook
Requires-Dist: argparse
